<?xml version="1.0" encoding="utf-8"?>
<UANodeSet xmlns="http://opcfoundation.org/UA/2011/03/UANodeSet.xsd">
  <NamespaceUris>
    <Uri>http://invernadero.org/clima</Uri>
  </NamespaceUris>

  <UAObjectType NodeId="ns=1;i=1001" BrowseName="1:ClimaType">
    <DisplayName>ClimaType</DisplayName>
    <References>
      <Reference ReferenceType="HasSubtype" IsForward="false">i=58</Reference>
    </References>
    <Children>
      <UAVariable NodeId="ns=1;i=1101" BrowseName="1:Temperatura" DataType="Float">
        <DisplayName>Temperatura</DisplayName>
        <Value>
          <Float>23.0</Float>
        </Value>
      </UAVariable>

      <UAVariable NodeId="ns=1;i=1102" BrowseName="1:Humedad" DataType="Float">
        <DisplayName>Humedad</DisplayName>
        <Value>
          <Float>65.0</Float>
        </Value>
      </UAVariable>

      <UAVariable NodeId="ns=1;i=1103" BrowseName="1:CO2" DataType="Float">
        <DisplayName>CO2</DisplayName>
        <Value>
          <Float>450.0</Float>
        </Value>
      </UAVariable>

      <UAVariable NodeId="ns=1;i=1104" BrowseName="1:IntensidadLuz" DataType="Float">
        <DisplayName>IntensidadLuz</DisplayName>
        <Value>
          <Float>800.0</Float>
        </Value>
      </UAVariable>

      <UAVariable NodeId="ns=1;i=1201" BrowseName="1:UbicacionZona" DataType="String">
        <DisplayName>UbicacionZona</DisplayName>
        <Value>
          <String>Zona A - Cultivo Principal</String>
        </Value>
      </UAVariable>

      <UAVariable NodeId="ns=1;i=1202" BrowseName="1:TimestampUltimaActualizacion" DataType="DateTime">
        <DisplayName>TimestampUltimaActualizacion</DisplayName>
        <Value>
          <DateTime>2025-11-13T10:43:55Z</DateTime>
        </Value>
      </UAVariable>

    </Children>
  </UAObjectType>
</UANodeSet>
